Eingang-0.0.2.data/scripts/eingang_create.sh
eingang/Eingang.py
eingang/Makefile
eingang/__init__.py
eingang/config.py.in
eingang/package.json
eingang/util.py
eingang/version.py
eingang/views.py
eingang/forms/__init__.py
eingang/forms/forms.py
eingang/models/Role.py
eingang/models/RolesUsers.py
eingang/models/User.py
eingang/models/__init__.py
eingang/models/util.py
eingang/static/eingang.css
eingang/templates/eingang/about.html
eingang/templates/eingang/head.html
eingang/templates/eingang/home.html
eingang/templates/eingang/index.html
eingang/templates/eingang/navbar.html
eingang/templates/eingang/tail.html
eingang/templates/security/_macros.html
eingang/templates/security/change_password.html
eingang/templates/security/forgot_password.html
eingang/templates/security/login_user.html
eingang/templates/security/reset_password.html
eingang/tests/app.py
eingang/tests/create_user.py
eingang/tests/database.py
eingang/tests/delete_user.py
eingang/tests/print_db.py
eingang/tests/test_app.py
eingang/tests/views.py
eingang/tests/templates/home.html
eingang/tests/templates/index.html
Eingang-0.0.2.dist-info/LICENSE
Eingang-0.0.2.dist-info/METADATA
Eingang-0.0.2.dist-info/WHEEL
Eingang-0.0.2.dist-info/top_level.txt
Eingang-0.0.2.dist-info/RECORD
