Metadata-Version: 2.1
Name: Eingang
Version: 0.0.2
Summary: Eingang.
Home-page: http://github.com/vmlaker/eingang
Author: Velimir Mlaker
Author-email: vel.i.mir.mlaker@gmail.com
License: MIT
Platform: any
Classifier: Framework :: Flask
Classifier: Topic :: Internet :: WWW/HTTP :: Dynamic Content
Classifier: Development Status :: 5 - Production/Stable
Classifier: License :: OSI Approved :: MIT License
Classifier: Programming Language :: Python
Classifier: Programming Language :: Python :: 2
Classifier: Programming Language :: Python :: 2.6
Classifier: Programming Language :: Python :: 2.7
Classifier: Programming Language :: Python :: 3
Classifier: Programming Language :: Python :: 3.4
Classifier: Programming Language :: Python :: 3.5
Classifier: Programming Language :: Python :: 3.6
Classifier: Environment :: Web Environment
Classifier: Intended Audience :: Developers
Classifier: Operating System :: OS Independent
Requires-Dist: Flask (==1.0.2)
Requires-Dist: Flask-Security (==3.0.0)
Requires-Dist: SQLAlchemy (==1.1.15)
